annotation_analysis/__init__.py
annotation_analysis/interannotator_metrics.py
annotation_analysis-0.0.0.3.dist-info/METADATA
annotation_analysis-0.0.0.3.dist-info/WHEEL
annotation_analysis-0.0.0.3.dist-info/top_level.txt
annotation_analysis-0.0.0.3.dist-info/RECORD
