Metadata-Version: 2.1
Name: annotation-analysis
Version: 0.0.0.3
Summary: Annotation Analysis
Home-page: https://github.com/ai-nikolai/annotation_analysis
Author: Nikolai Rozanov
Author-email: nikolai.rozanov@gmail.com
License: GPL 2.0
Requires-Dist: numpy
Requires-Dist: krippendorff
Requires-Dist: statsmodels
